AUTHORS.txt
LICENSE
MANIFEST.in
README.md
requirements.txt
setup.cfg
setup.py
compat/__init__.py
compat/json_response.py
compat/models.py
compat/shortcuts.py
compat/docs/__init__.py
compat/docs/compatibility.py
compat/templatetags/__init__.py
compat/templatetags/compat.py
compat/tests/__init__.py
compat/tests/manage_settings.py
compat/tests/south_settings.py
compat/tests/test_compat.py
compat/tests/test_module_loading.py
compat/tests/urls.py
compat/tests/test_app/__init__.py
compat/tests/test_app/models.py
compat/tests/test_app/templatetags/__init__.py
compat/tests/test_app/templatetags/test_app_tags.py
compat/tests/utils_tests/__init__.py
compat/tests/utils_tests/test_no_submodule.py
compat/tests/utils_tests/not_installed/__init__.py
compat/tests/utils_tests/not_installed/models.py
compat/tests/utils_tests/test_module/__init__.py
compat/tests/utils_tests/test_module/another_bad_module.py
compat/tests/utils_tests/test_module/another_good_module.py
compat/tests/utils_tests/test_module/bad_module.py
compat/tests/utils_tests/test_module/good_module.py
django_compat.egg-info/PKG-INFO
django_compat.egg-info/SOURCES.txt
django_compat.egg-info/dependency_links.txt
django_compat.egg-info/requires.txt
django_compat.egg-info/top_level.txt