Metadata-Version: 1.1
Name: django-compat
Version: 1.0.14
Summary: For- and backwards compatibility layer for Django 1.4, 1.7, 1.8, 1.9, and 1.10
Home-page: https://github.com/arteria/django-compat
Author: arteria GmbH
Author-email: admin@arteria.ch
License: MIT
Platform: UNKNOWN
Classifier: Development Status :: 5 - Production/Stable
Classifier: Framework :: Django
Classifier: License :: OSI Approved :: MIT License
Classifier: Framework :: Django
Classifier: Framework :: Django :: 1.4
Classifier: Framework :: Django :: 1.6
Classifier: Framework :: Django :: 1.7
Classifier: Framework :: Django :: 1.8
Classifier: Framework :: Django :: 1.9
Classifier: Framework :: Django :: 1.10
Classifier: Programming Language :: Python
Classifier: Programming Language :: Python :: 2
Classifier: Programming Language :: Python :: 3
